miyadaiku/themes/bootstrap4/__init__.py
miyadaiku/themes/bootstrap4/__version__.py
miyadaiku/themes/bootstrap4/config.yml
miyadaiku/themes/bootstrap4/externals/css/bootstrap.css
miyadaiku/themes/bootstrap4/externals/css/bootstrap.min.css
miyadaiku/themes/bootstrap4/externals/js/bootstrap.bundle.js
miyadaiku/themes/bootstrap4/externals/js/bootstrap.bundle.min.js
miyadaiku/themes/bootstrap4/externals/js/bootstrap.js
miyadaiku/themes/bootstrap4/externals/js/bootstrap.min.js
miyadaiku/themes/bootstrap4/templates/macros.html
miyadaiku.themes.bootstrap4-0.10.dist-info/METADATA
miyadaiku.themes.bootstrap4-0.10.dist-info/WHEEL
miyadaiku.themes.bootstrap4-0.10.dist-info/top_level.txt
miyadaiku.themes.bootstrap4-0.10.dist-info/RECORD
