Metadata-Version: 2.1
Name: miyadaiku.themes.bootstrap4
Version: 0.10
Summary: Bootstrap 4 files for miyadaiku static site generator
Home-page: https://github.com/miyadaiku/miyadaiku-themes-bootstrap4
Author: Atsuo Ishimoto
Author-email: UNKNOWN
License: MIT
Project-URL: Miyadaiku, https://miyadaiku.github.io/
Platform: UNKNOWN
Classifier: Programming Language :: Python :: 3
Classifier: Programming Language :: Python :: 3.6
Classifier: Programming Language :: Python :: 3.7
Requires-Dist: miyadaiku
Requires-Dist: miyadaiku.themes.jquery
Requires-Dist: miyadaiku.themes.popper-js
